stockgetter2/__init__.py
stockgetter2/Getter/mstBrand.py
stockgetter2/Getter/seleniumTest.py
stockgetter2/Getter/trnDayStockPrice.py
stockgetter2/Getter/Base/baseGetter.py
stockgetter2/Library/stockgetterConfig.py
stockgetter2/Library/stockgetterConfiger.py
stockgetter2/Library/stockgetterController.py
stockgetter2/Library/stockgetterDeclare.py
stockgetter2/Library/stockgetterException.py
stockgetter2/Library/stockgetterGlobals.py
stockgetter2/Library/stockgetterMailer.py
stockgetter2/Models/mstBrand.py
stockgetter2/Models/trnDayStockPrice.py
stockgetter2/Register/register_StockData.py
stockgetter2/Register/Base/baseRegister.py
stockgetter2-1.0.19.dist-info/METADATA
stockgetter2-1.0.19.dist-info/WHEEL
stockgetter2-1.0.19.dist-info/top_level.txt
stockgetter2-1.0.19.dist-info/RECORD
