Metadata-Version: 2.1
Name: stockgetter2
Version: 1.0.19
Summary: stockgetter2 Package
Home-page: https://github.com/kaioman/stockgetter2.git
Author: unchainworks
Author-email: kajin0318@gmail.com
License: BSD-3-Clause
Keywords: stockgetter2
Classifier: Development Status :: 5 - Production/Stable
Classifier: License :: OSI Approved :: BSD License
Classifier: Programming Language :: Python
Classifier: Programming Language :: Python :: 3
Classifier: Programming Language :: Python :: 3.4
Classifier: Programming Language :: Python :: 3.5
Classifier: Programming Language :: Python :: 3.6
Classifier: Programming Language :: Python :: 3.7
Classifier: Programming Language :: Python :: 3.8
Classifier: Programming Language :: Python :: 3.9
Classifier: Topic :: Database
Classifier: Topic :: Software Development :: Libraries :: Python Modules
Requires-Dist: beautifulsoup4 (==4.11.1)
Requires-Dist: bleach (==5.0.1)
Requires-Dist: bs4 (==0.0.1)
Requires-Dist: certifi (==2022.12.7)
Requires-Dist: charset-normalizer (==2.1.1)
Requires-Dist: commonmark (==0.9.1)
Requires-Dist: docutils (==0.19)
Requires-Dist: et-xmlfile (==1.1.0)
Requires-Dist: greenlet (==2.0.1)
Requires-Dist: idna (==3.4)
Requires-Dist: importlib-metadata (==6.0.0)
Requires-Dist: jaraco.classes (==3.2.3)
Requires-Dist: keyring (==23.13.1)
Requires-Dist: LibHanger
Requires-Dist: lxml (==4.9.1)
Requires-Dist: more-itertools (==9.0.0)
Requires-Dist: numpy (==1.23.4)
Requires-Dist: openpyxl (==3.0.10)
Requires-Dist: pandas (==1.5.1)
Requires-Dist: Pillow (==9.3.0)
Requires-Dist: pkginfo (==1.9.5)
Requires-Dist: psutil (==5.9.4)
Requires-Dist: psycopg2 (==2.9.5)
Requires-Dist: Pygments (==2.14.0)
Requires-Dist: python-dateutil (==2.8.2)
Requires-Dist: pytz (==2022.6)
Requires-Dist: pywin32-ctypes (==0.2.0)
Requires-Dist: readme-renderer (==37.3)
Requires-Dist: requests (==2.28.1)
Requires-Dist: requests-toolbelt (==0.10.1)
Requires-Dist: rfc3986 (==2.0.0)
Requires-Dist: rich (==13.0.1)
Requires-Dist: Scrapinger
Requires-Dist: selenium (==3.141.0)
Requires-Dist: six (==1.16.0)
Requires-Dist: soupsieve (==2.3.2.post1)
Requires-Dist: SQLAlchemy (==1.4.44)
Requires-Dist: twine (==4.0.2)
Requires-Dist: urllib3 (==1.26.12)
Requires-Dist: webencodings (==0.5.1)
Requires-Dist: xlrd (==2.0.1)
Requires-Dist: zipp (==3.11.0)
